{
  "project_info": {
    "project_number": "923452020193",
    "project_id": "chatbot-a9d5b",
    "storage_bucket": "chatbot-a9d5b.appspot.com"
  },
  "client": [
    {
      "client_info": {
        "mobilesdk_app_id": "1:923452020193:android:c7a92ba3439d6e9811eea0",
        "android_client_info": {
          "package_name": "com.mohamedIsmail.chatbot"
        }
      },
      "oauth_client": [
        {
          "client_id": "923452020193-rgd3f9jfjffakshfh09djbt2tjeckep3.apps.googleusercontent.com",
          "client_type": 3
        }
      ],
      "api_key": [
        {
          "current_key": "AIzaSyC-xksc6DzaETjHlGN60KJHTyJIDD81SQw"
        }
      ],
      "services": {
        "appinvite_service": {
          "other_platform_oauth_client": [
            {
              "client_id": "923452020193-rgd3f9jfjffakshfh09djbt2tjeckep3.apps.googleusercontent.com",
              "client_type": 3
            }
          ]
        }
      }
    }
  ],
  "configuration_version": "1"
}